{"metadata": {"dbt_schema_version": "https://schemas.getdbt.com/dbt/run-results/v6.json", "dbt_version": "1.11.7", "generated_at": "2026-03-22T15:04:05.569762Z", "invocation_id": "3f83c66a-a305-457f-82a5-0a8a4ff6dd6d", "invocation_started_at": "2026-03-22T15:04:03.174365Z", "env": {}}, "results": [{"status": "success", "timing": [{"name": "compile", "started_at": "2026-03-22T15:04:05.494097Z", "completed_at": "2026-03-22T15:04:05.500863Z"}, {"name": "execute", "started_at": "2026-03-22T15:04:05.501201Z", "completed_at": "2026-03-22T15:04:05.560610Z"}], "thread_id": "Thread-1 (worker)", "execution_time": 0.06761670112609863, "adapter_response": {"_message": "OK"}, "message": "OK", "failures": null, "unique_id": "model.telemetry_dbt.curated_telemetry", "compiled": true, "compiled_code": "-- Este modelo lee directamente del Parquet generado por Spark\nWITH raw_data AS (\n    SELECT * \n    FROM read_parquet('/home/diegokernel/proyectos/spark_airflow_telemetry/data/processed/vehicle_telemetry_agg/*.parquet')\n)\n\nSELECT \n    VehId,\n    Trip,\n    avg_speed_kmh,\n    max_rpm,\n    total_fuel_rate,\n    -- Creamos una m\u00e9trica inventada\n    CASE \n        WHEN max_rpm > 3000 THEN 'High Intensity'\n        WHEN max_rpm > 2000 THEN 'Normal'\n        ELSE 'Eco'\n    END AS driving_style\nFROM raw_data\nWHERE total_fuel_rate IS NOT NULL OR avg_speed_kmh > 0", "relation_name": "\"telemetry_data\".\"main\".\"curated_telemetry\"", "batch_results": null}], "elapsed_time": 1.0699634552001953, "args": {"upload_to_artifacts_ingest_api": false, "state_modified_compare_more_unrendered_values": false, "require_batched_execution_for_custom_microbatch_strategy": false, "state_modified_compare_vars": false, "require_yaml_configuration_for_mf_time_spines": false, "profiles_dir": ".", "log_format": "default", "exclude": [], "strict_mode": false, "require_generic_test_arguments_property": true, "select": [], "send_anonymous_usage_stats": true, "cache_selected_only": false, "introspect": true, "which": "run", "defer": false, "require_resource_names_without_spaces": true, "log_format_file": "debug", "require_explicit_package_overrides_for_builtin_materializations": true, "show_all_deprecations": false, "printer_width": 80, "vars": {}, "log_file_max_bytes": 10485760, "empty": false, "quiet": false, "require_all_warnings_handled_by_warn_error": false, "use_colors_file": true, "indirect_selection": "eager", "partial_parse": true, "version_check": true, "warn_error_options": {"error": [], "warn": [], "silence": []}, "log_level_file": "debug", "macro_debugging": false, "populate_cache": true, "require_unique_project_resource_names": false, "log_path": "/home/diegokernel/proyectos/spark_airflow_telemetry/telemetry_dbt/logs", "project_dir": "/home/diegokernel/proyectos/spark_airflow_telemetry/telemetry_dbt", "source_freshness_run_project_hooks": true, "use_fast_test_edges": false, "write_json": true, "show_resource_report": false, "validate_macro_args": false, "partial_parse_file_diff": true, "skip_nodes_if_on_run_start_fails": false, "static_parser": true, "favor_state": false, "print": true, "use_colors": true, "require_nested_cumulative_type_params": false, "invocation_command": "dbt run --profiles-dir .", "log_level": "info", "require_ref_searches_node_package_before_root": false}}